setup.cfg
setup.py
penelope/__init__.py
penelope/config.py
penelope/middleware/__init__.py
penelope/middleware/auth.py
penelope/middleware/cors.py
penelope/middleware/json.py
penelope/middleware/tests.py
penelope/resources/__init__.py
penelope/resources/base_handlers.py
penelope/utils/__init__.py
penelope/utils/auth.py
penelope/utils/misc.py
penelope/utils/tests.py
penelope_falcon.egg-info/PKG-INFO
penelope_falcon.egg-info/SOURCES.txt
penelope_falcon.egg-info/dependency_links.txt
penelope_falcon.egg-info/requires.txt
penelope_falcon.egg-info/top_level.txt