Metadata-Version: 1.0
Name: penelope-falcon
Version: 0.0.4
Summary: My collection of assorted utils for the Falcon Framework (http://falconframework.org/)
Home-page: https://github.com/projectweekend/penelope
Author: Brian Hines
Author-email: brian@projectweekend.net
License: UNKNOWN
Platform: UNKNOWN
